relationalai_gnns/CHANGELOG.md
relationalai_gnns/LICENCE
relationalai_gnns/README.md
relationalai_gnns/__init__.py
relationalai_gnns/_version.py
relationalai_gnns/instructions_to_add_sdk_to_sf_notebooks.MD
relationalai_gnns/common/__init__.py
relationalai_gnns/common/dataset_model.py
relationalai_gnns/common/exceptions.py
relationalai_gnns/common/export.py
relationalai_gnns/common/job_models.py
relationalai_gnns/core/__init__.py
relationalai_gnns/core/api_request_handler.py
relationalai_gnns/core/config_trainer.py
relationalai_gnns/core/connector.py
relationalai_gnns/core/custom_sqlalchemy_dtypes.py
relationalai_gnns/core/dataset.py
relationalai_gnns/core/gnn_table.py
relationalai_gnns/core/job_manager.py
relationalai_gnns/core/metrics.py
relationalai_gnns/core/model_manager.py
relationalai_gnns/core/provider.py
relationalai_gnns/core/task.py
relationalai_gnns/core/trainer.py
relationalai_gnns/core/types.py
relationalai_gnns/core/utils.py
relationalai_gnns/external/__init__.py
relationalai_gnns/external/db_diagram.py
relationalai_gnns/external/model_diagram.py
relationalai_gnns-0.0.4.dist-info/METADATA
relationalai_gnns-0.0.4.dist-info/WHEEL
relationalai_gnns-0.0.4.dist-info/RECORD
