Metadata-Version: 2.4
Name: relationalai-gnns
Version: 0.0.4
Summary: GNN Relational Learning Engine SDK
Author-email: RelationalAI <support@relational.ai>
License: Apache-2.0
Requires-Python: >=3.10
Requires-Dist: pandas>=2.3.3
Requires-Dist: pydantic>=2.11.0
Requires-Dist: pydot>=4.0.1
Requires-Dist: python-dotenv>=1.2.1
Requires-Dist: pyyaml>=6.0.3
Requires-Dist: requests>=2.32.5
Requires-Dist: snowflake-snowpark-python>=1.39.1
Requires-Dist: sqlalchemy>=2.0.45
Requires-Dist: tabulate>=0.9.0
